cacao_accounting/I18N.py
cacao_accounting/__init__.py
cacao_accounting/__main__.py
cacao_accounting/cli.py
cacao_accounting/config.py
cacao_accounting/decorators.py
cacao_accounting/desktop.py
cacao_accounting/loggin.py
cacao_accounting/metadata.py
cacao_accounting/modulos.py
cacao_accounting/server.py
cacao_accounting/version.py
cacao_accounting/admin/__init__.py
cacao_accounting/admin/registros/__init__.py
cacao_accounting/admin/templates/admin.html
cacao_accounting/admin/templates/admin/modulos.html
cacao_accounting/ajax/__init__.py
cacao_accounting/app/__init__.py
cacao_accounting/app/templates/app.html
cacao_accounting/app/templates/development.html
cacao_accounting/auth/__init__.py
cacao_accounting/auth/forms.py
cacao_accounting/auth/permisos.py
cacao_accounting/auth/roles.py
cacao_accounting/auth/registros/__init__.py
cacao_accounting/auth/templates/login.html
cacao_accounting/auth/templates/test_roles.html
cacao_accounting/bancos/__init__.py
cacao_accounting/bancos/templates/bancos.html
cacao_accounting/compras/__init__.py
cacao_accounting/compras/templates/compras.html
cacao_accounting/contabilidad/__init__.py
cacao_accounting/contabilidad/auxiliares.py
cacao_accounting/contabilidad/forms.py
cacao_accounting/contabilidad/ctas/__init__.py
cacao_accounting/contabilidad/ctas/catalogos/base.csv
cacao_accounting/contabilidad/registros/__init__.py
cacao_accounting/contabilidad/registros/ccosto.py
cacao_accounting/contabilidad/registros/cuenta.py
cacao_accounting/contabilidad/registros/entidad.py
cacao_accounting/contabilidad/registros/moneda.py
cacao_accounting/contabilidad/registros/periodo.py
cacao_accounting/contabilidad/registros/proyecto.py
cacao_accounting/contabilidad/registros/tasa_cambio.py
cacao_accounting/contabilidad/registros/unidad.py
cacao_accounting/contabilidad/templates/contabilidad.html
cacao_accounting/contabilidad/templates/contabilidad/centro-costo.html
cacao_accounting/contabilidad/templates/contabilidad/centro-costo_lista.html
staging_cacao_accounting-0.0.1b20240511.dist-info/LICENSE
staging_cacao_accounting-0.0.1b20240511.dist-info/Licencias_de_Terceros.md
staging_cacao_accounting-0.0.1b20240511.dist-info/METADATA
staging_cacao_accounting-0.0.1b20240511.dist-info/WHEEL
staging_cacao_accounting-0.0.1b20240511.dist-info/entry_points.txt
staging_cacao_accounting-0.0.1b20240511.dist-info/top_level.txt
staging_cacao_accounting-0.0.1b20240511.dist-info/RECORD
