Metadata-Version: 2.1
Name: staging-cacao-accounting
Version: 0.0.1b20240511
Summary: Accounting solution for the management of Accounts Payable, Accounts Receivable, Inventory, Treasury and General Accounting.
Author-email: William Moreno Reyes <williamjmorenor@gmail.com>, BMO Soluciones <development@bmogroup.solutions>
License: Apache License
Keywords: accounting
Classifier: Development Status :: 1 - Planning
Classifier: Framework :: Flask
Classifier: License :: OSI Approved :: Apache Software License
Classifier: Natural Language :: Spanish
Classifier: Operating System :: OS Independent
Classifier: Programming Language :: Python :: 3 :: Only
Classifier: Programming Language :: Python :: 3.8
Classifier: Programming Language :: Python :: 3.9
Classifier: Programming Language :: Python :: 3.10
Classifier: Programming Language :: Python :: 3.11
Classifier: Programming Language :: Python :: 3.12
Classifier: Programming Language :: Python :: Implementation :: CPython
Requires-Python: >=3.8
License-File: LICENSE
License-File: Licencias_de_Terceros.md
Requires-Dist: alembic
Requires-Dist: bcrypt
Requires-Dist: babel
Requires-Dist: Flask
Requires-Dist: Flask-Alembic
Requires-Dist: flask-babel
Requires-Dist: flask-login
Requires-Dist: flask-sqlalchemy
Requires-Dist: flask-wtf
Requires-Dist: loguru
Requires-Dist: lxml
Requires-Dist: pdf-reports
Requires-Dist: openpyxl
Requires-Dist: sqlalchemy
Requires-Dist: teritorio
Requires-Dist: waitress
Requires-Dist: wtforms
Requires-Dist: WTForms-SQLAlchemy
Requires-Dist: pillow
Requires-Dist: pg8000
Requires-Dist: PyMySQL
Requires-Dist: cryptography
